{"trial_id": "05", "hyperparameters": {"space": [{"class_name": "Int", "config": {"name": "lstm_units", "default": null, "conditions": [], "min_value": 32, "max_value": 256, "step": 32, "sampling": "linear"}}, {"class_name": "Float", "config": {"name": "lstm_dropout_rate", "default": 0.0, "conditions": [], "min_value": 0.0, "max_value": 0.5, "step": 0.05, "sampling": "linear"}}, {"class_name": "Int", "config": {"name": "cnn_filters", "default": null, "conditions": [], "min_value": 32, "max_value": 256, "step": 32, "sampling": "linear"}}, {"class_name": "Int", "config": {"name": "kernel_size", "default": null, "conditions": [], "min_value": 3, "max_value": 7, "step": 1, "sampling": "linear"}}, {"class_name": "Int", "config": {"name": "dense_units", "default": null, "conditions": [], "min_value": 10, "max_value": 256, "step": 10, "sampling": "linear"}}], "values": {"lstm_units": 224, "lstm_dropout_rate": 0.45, "cnn_filters": 256, "kernel_size": 5, "dense_units": 150}}, "metrics": {"metrics": {"loss": {"direction": "min", "observations": [{"value": [16.57549285888672], "step": 86}]}, "val_loss": {"direction": "min", "observations": [{"value": [0.8785926699638367], "step": 86}]}}}, "score": 0.8785926699638367, "best_step": 86, "status": "COMPLETED", "message": null}